CONTRIBUTORS.txt
MANIFEST.in
README.rst
requirements.txt
setup.py
tox.ini
gipsy/__init__.py
gipsy/modeltranslation/__init__.py
gipsy/modeltranslation/pages/__init__.py
gipsy/modeltranslation/pages/admin.py
gipsy/modeltranslation/pages/apps.py
gipsy/modeltranslation/pages/forms.py
gipsy/modeltranslation/pages/managers.py
gipsy/modeltranslation/pages/models.py
gipsy/modeltranslation/pages/tests.py
gipsy/modeltranslation/pages/translation.py
gipsy/modeltranslation/pages/urls.py
gipsy/modeltranslation/pages/views.py
gipsy/modeltranslation/pages/.ropeproject/config.py
gipsy/modeltranslation/pages/.ropeproject/globalnames
gipsy/modeltranslation/pages/.ropeproject/history
gipsy/modeltranslation/pages/.ropeproject/objectdb
gipsy/modeltranslation/pages/migrations/0001_initial.py
gipsy/modeltranslation/pages/migrations/__init__.py
gipsy_modeltranslation_pages.egg-info/PKG-INFO
gipsy_modeltranslation_pages.egg-info/SOURCES.txt
gipsy_modeltranslation_pages.egg-info/dependency_links.txt
gipsy_modeltranslation_pages.egg-info/namespace_packages.txt
gipsy_modeltranslation_pages.egg-info/requires.txt
gipsy_modeltranslation_pages.egg-info/top_level.txt
requirements/base.txt
requirements/dev.txt
requirements/production.txt
requirements/test.txt